vbinds/__init__.py
vbinds/__init__.pyi
vbinds/app.py
vbinds/app.pyi
vbinds/entry.py
vbinds/entry.pyi
vbinds/icons.py
vbinds/icons.pyi
vbinds/classes/__init__.py
vbinds/classes/__init__.pyi
vbinds/classes/cache.py
vbinds/classes/cache.pyi
vbinds/classes/class_data_engine.py
vbinds/classes/class_data_engine.pyi
vbinds/classes/engine.py
vbinds/classes/engine.pyi
vbinds/classes/icon_cache.py
vbinds/classes/icon_cache.pyi
vbinds/classes/playable_class.py
vbinds/classes/playable_class.pyi
vbinds/classes/query_engine.py
vbinds/classes/query_engine.pyi
vbinds/classes/spec_data_engine.py
vbinds/classes/spec_data_engine.pyi
vbinds/classes/specialization.py
vbinds/classes/specialization.pyi
vbinds/classes/talent.py
vbinds/classes/talent.pyi
vbinds/classes/token_engine.py
vbinds/classes/token_engine.pyi
vbinds/enums/__init__.py
vbinds/enums/__init__.pyi
blizzard_api-0.3.4.dist-info/LICENSE
blizzard_api-0.3.4.dist-info/METADATA
blizzard_api-0.3.4.dist-info/WHEEL
blizzard_api-0.3.4.dist-info/entry_points.txt
blizzard_api-0.3.4.dist-info/top_level.txt
blizzard_api-0.3.4.dist-info/RECORD
