Metadata-Version: 2.1
Name: blizzard-api
Version: 0.3.4
Summary: Interact with Blizard's game-data API.
Home-page: https://github.com/vkottler/keybinds/tree/master/wow
Author: Vaughn Kottler
Author-email: vaughnkottler@gmail.com
License: UNKNOWN
Platform: UNKNOWN
Classifier: License :: OSI Approved :: MIT License
Classifier: Operating System :: OS Independent
Classifier: Programming Language :: Python :: 3.7
Classifier: Programming Language :: Python :: 3.8
Classifier: Programming Language :: Python :: 3.9
Requires-Python: >=3.7
License-File: LICENSE
Requires-Dist: requests
